tree_sitter_vie-0.2.3.dist-info/RECORD
tree_sitter_vie-0.2.3.dist-info/WHEEL
tree_sitter_vie-0.2.3.dist-info/top_level.txt
tree_sitter_vie-0.2.3.dist-info/METADATA
tree_sitter_vie-0.2.3.dist-info/licenses/LICENSE
tree_sitter_vie/__init__.pyi
tree_sitter_vie/binding.c
tree_sitter_vie/__init__.py
tree_sitter_vie/py.typed
tree_sitter_vie/_binding.abi3.so
tree_sitter_vie/queries/highlights.scm
tree_sitter_vie/queries/injections.scm
