Metadata-Version: 2.4
Name: tree-sitter-vie
Version: 0.2.3
Summary: Vie grammar for tree-sitter
Author: nickshiro, skewb1k
License: MIT
Project-URL: Homepage, https://github.com/vietmpl/tree-sitter-vie
Keywords: incremental,parsing,tree-sitter,vie
Classifier: Intended Audience :: Developers
Classifier: Topic :: Software Development :: Compilers
Classifier: Topic :: Text Processing :: Linguistic
Classifier: Typing :: Typed
Requires-Python: >=3.10
License-File: LICENSE
Provides-Extra: core
Requires-Dist: tree-sitter~=0.24; extra == "core"
Dynamic: license-file
